{"id":"ML 11888 no 08.01.26","date":"08.01.26","totalVolume":0,"totalContainers":0,"stops":[{"order":1,"address":"Zanderu kapi V04 sektors","binCode":"21684","dayPattern":"x2x4xxx","frequency":"pasūt","timeSpent":16.34,"volume":2.2,"containers":2},{"order":2,"address":"Zanderu kapi 1.vieta","binCode":"21683","dayPattern":"x2x4xxx","frequency":"pasūt","timeSpent":16.34,"volume":4.4,"containers":4},{"order":3,"address":"Baložu kapi 1.vieta","binCode":"21669","dayPattern":"x2x4xxx","frequency":"pasūt","timeSpent":16.34,"volume":4.4,"containers":4},{"order":4,"address":"Baložu kapi 4.sektors, pretī 1.vietai","binCode":"21671","dayPattern":"x2x4xxx","frequency":"pasūt","timeSpent":16.34,"volume":2.2,"containers":2},{"order":5,"address":"Baložu kapi 4.vieta","binCode":"21670","dayPattern":"x2x4xxx","frequency":"pasūt","timeSpent":16.34,"volume":4.4,"containers":4},{"order":6,"address":"Meža kapi 1.sektors","binCode":"21679","dayPattern":"x2x4xxx","frequency":"pasūt","timeSpent":16.34,"volume":3.3,"containers":3},{"order":7,"address":"Meža kapi 2.vieta","binCode":"21680","dayPattern":"x2x4xxx","frequency":"pasūt","timeSpent":16.34,"volume":6.6,"containers":6},{"order":8,"address":"Meža kapi 4.vieta","binCode":"21682","dayPattern":"x2x4xxx","frequency":"pasūt","timeSpent":16.34,"volume":4.4,"containers":4},{"order":9,"address":"Bērzu kapi 7.vieta","binCode":"21673","dayPattern":"x2x4xxx","frequency":"pasūt","timeSpent":16.34,"volume":3.3,"containers":3},{"order":10,"address":"Bērzu kapi 6.vieta","binCode":"21675","dayPattern":"x2x4xxx","frequency":"pasūt","timeSpent":16.34,"volume":3.3,"containers":3},{"order":11,"address":"Bērzu kapi 1.vieta","binCode":"21672","dayPattern":"x2x4xxx","frequency":"pasūt","timeSpent":16.34,"volume":3.3,"containers":3},{"order":12,"address":"Bērzu kapi 5.vieta","binCode":"21676","dayPattern":"x2x4xxx","frequency":"pasūt","timeSpent":16.34,"volume":4.4,"containers":4},{"order":13,"address":"Bērzu kapi 7./8.sektors","binCode":"21677","dayPattern":"x2x4xxx","frequency":"pasūt","timeSpent":16.34,"volume":1.1,"containers":1},{"order":14,"address":"Bērzu kapi 8.sektors","binCode":"21678","dayPattern":"x2x4xxx","frequency":"pasūt","timeSpent":16.34,"volume":1.1,"containers":1}]}